LICENSE
MANIFEST.in
README.md
setup.py
django_posts.egg-info/PKG-INFO
django_posts.egg-info/SOURCES.txt
django_posts.egg-info/dependency_links.txt
django_posts.egg-info/requires.txt
django_posts.egg-info/top_level.txt
posts/__init__.py
posts/admin.py
posts/models.py
posts/urls.py
posts/views.py
posts/templatetags/__init__.py
posts/templatetags/post_tags.py
posts/tests/__init__.py
posts/tests/runtests.py
posts/tests/urls.py