Metadata-Version: 1.0
Name: django-posts
Version: 0.2.0
Summary: A generic posts app for django
Home-page: https://github.com/byteweaver/django-posts
Author: noxan
Author-email: contact@byteweaver.net
License: MIT License
Platform: UNKNOWN
